flake8_diff_only/__init__.py
flake8_diff_only/checker.py
flake8_diff_only/patch.py
flake8_diff_only/types.py
flake8_diff_only/utils.py
flake8_diff_only-0.1.9.dist-info/LICENSE.md
flake8_diff_only-0.1.9.dist-info/METADATA
flake8_diff_only-0.1.9.dist-info/WHEEL
flake8_diff_only-0.1.9.dist-info/entry_points.txt
flake8_diff_only-0.1.9.dist-info/RECORD
